Metadata-Version: 2.1
Name: websupportsk
Version: 0.1.2
Summary: Python wrapper for the Websupport.sk REST API
Home-page: https://github.com/JozefGalbicka/python-websupportsk
Author: Jozef Galbicka
Author-email: alerts.cryp@gmail.com
License: MIT
Platform: UNKNOWN
Classifier: Development Status :: 3 - Alpha
Classifier: Intended Audience :: System Administrators
Classifier: License :: OSI Approved :: MIT License
Classifier: Programming Language :: Python
Classifier: Programming Language :: Python :: 3
Classifier: Programming Language :: Python :: 3.8
Classifier: Programming Language :: Python :: 3.9
Classifier: Topic :: Software Development
Classifier: Topic :: Software Development :: Libraries :: Python Modules
Classifier: Topic :: Internet :: Name Service (DNS)
